LICENSE
MANIFEST.in
README.rst
dshield.py
setup.py
dshield.egg-info/PKG-INFO
dshield.egg-info/SOURCES.txt
dshield.egg-info/dependency_links.txt
dshield.egg-info/pbr.json
dshield.egg-info/requires.txt
dshield.egg-info/top_level.txt