Metadata-Version: 1.1
Name: dshield
Version: 0.2.1
Summary: A Pythonic interface to the Internet Storm Center / DShield API.
Home-page: https://github.com/rshipp/python-dshield/
Author: Ryan Shipp
Author-email: python@rshipp.com
License: BSD
Platform: UNKNOWN
Classifier: Intended Audience :: Developers
Classifier: Intended Audience :: Information Technology
Classifier: Intended Audience :: System Administrators
Classifier: License :: OSI Approved :: BSD License
Classifier: Operating System :: OS Independent
Classifier: Programming Language :: Python
Classifier: Topic :: Software Development :: Libraries
Classifier: Topic :: Internet
